chatbase_track/__init__.py
chatbase_track/aiogram.py
chatbase_track/backend/__init__.py
chatbase_track/backend/aiohttp.py
chatbase_track/backend/base.py
chatbase_track/backend/httpx.py
chatbase_track/backend/requests.py
chatbase_track/chatbase.py
chatbase_track/types/__init__.py
chatbase_track/types/base.py
chatbase_track/types/message.py
chatbase_track/types/message_type.py
chatbase_track/types/response.py
chatbase_track-0.1.0.dist-info/WHEEL
chatbase_track-0.1.0.dist-info/METADATA
chatbase_track-0.1.0.dist-info/RECORD
