Metadata-Version: 2.1
Name: chatbase-track
Version: 0.1.0
Summary: 
Author: Alex Root Junior
Author-email: jroot.junior@gmail.com
Requires-Python: >=3.7,<4.0
Classifier: Programming Language :: Python :: 3
Classifier: Programming Language :: Python :: 3.7
Classifier: Programming Language :: Python :: 3.8
Provides-Extra: aiogram
Provides-Extra: aiohttp
Provides-Extra: httpx
Provides-Extra: requests
Requires-Dist: aiogram (>=2.6.1,<3.0.0); extra == "aiogram"
Requires-Dist: aiohttp (>=3.6.2,<4.0.0); extra == "aiohttp"
Requires-Dist: httpx (>=0.11.1,<0.12.0); extra == "httpx"
Requires-Dist: pydantic (>=1.4,<2.0)
Requires-Dist: requests (>=2.22.0,<3.0.0); extra == "requests"
